operations/__init__.py
operations/flowback.py
qep_info_objects-0.0.6.dist-info/METADATA
qep_info_objects-0.0.6.dist-info/WHEEL
qep_info_objects-0.0.6.dist-info/top_level.txt
qep_info_objects-0.0.6.dist-info/RECORD
