Metadata-Version: 2.1
Name: qep-info-objects
Version: 0.0.6
Summary: Data class packages for information objects
Author: Pankaj Sharma
Author-email: psharma@quantumep.com
License: UNKNOWN
Platform: UNKNOWN
Classifier: Programming Language :: Python :: 3
Classifier: License :: OSI Approved :: MIT License
Classifier: Operating System :: OS Independent
Requires-Python: >=3.8
